<?xml version="1.0"?>
<!DOCTYPE hibernate-mapping PUBLIC
        "-//Hibernate/Hibernate Mapping DTD 3.0//EN"
        "http://www.hibernate.org/dtd/hibernate-mapping-3.0.dtd">
<hibernate-mapping>

    <class name="org.bitpimp.camelHibernate.Person" table="People">

        <id name="id">
            <generator class="native"/>
        </id>

        <property name="firstName" length="32"/>
        <property name="lastName" length="32"/>
        <property name="city" length="50"/>
    </class>

</hibernate-mapping>